opendataloader_pdf/LICENSE
opendataloader_pdf/NOTICE.md
opendataloader_pdf/__init__.py
opendataloader_pdf/__main__.py
opendataloader_pdf/cli_options_generated.py
opendataloader_pdf/convert_generated.py
opendataloader_pdf/hybrid_server.py
opendataloader_pdf/runner.py
opendataloader_pdf/wrapper.py
opendataloader_pdf/THIRD_PARTY/THIRD_PARTY_LICENSES.md
opendataloader_pdf/THIRD_PARTY/THIRD_PARTY_NOTICES.md
opendataloader_pdf/THIRD_PARTY/licenses/Apache-2.0.txt
opendataloader_pdf/THIRD_PARTY/licenses/BSD-3-Clause.txt
opendataloader_pdf/THIRD_PARTY/licenses/CDDL-1.1.txt
opendataloader_pdf/THIRD_PARTY/licenses/EDL-1.0.txt
opendataloader_pdf/THIRD_PARTY/licenses/EPL-2.0.txt
opendataloader_pdf/THIRD_PARTY/licenses/LICENSE-JJ2000.txt
opendataloader_pdf/THIRD_PARTY/licenses/MIT.txt
opendataloader_pdf/THIRD_PARTY/licenses/MPL-2.0.txt
opendataloader_pdf/THIRD_PARTY/licenses/Plexus Classworlds License.txt
opendataloader_pdf/jar/opendataloader-pdf-cli.jar
opendataloader_pdf-1.9.1.dist-info/METADATA
opendataloader_pdf-1.9.1.dist-info/WHEEL
opendataloader_pdf-1.9.1.dist-info/entry_points.txt
opendataloader_pdf-1.9.1.dist-info/RECORD
