Metadata-Version: 2.4
Name: opendataloader-pdf
Version: 1.9.1
Summary: A Python wrapper for the opendataloader-pdf Java CLI.
Project-URL: Homepage, https://github.com/opendataloader-project/opendataloader-pdf
Author-email: opendataloader-project <open.dataloader@hancom.com>
License-Expression: MPL-2.0
Classifier: Operating System :: OS Independent
Classifier: Programming Language :: Python :: 3
Requires-Python: >=3.10
Provides-Extra: hybrid
Requires-Dist: docling[easyocr]>=2.0.0; extra == 'hybrid'
Requires-Dist: fastapi>=0.100.0; extra == 'hybrid'
Requires-Dist: python-multipart>=0.0.6; extra == 'hybrid'
Requires-Dist: uvicorn>=0.20.0; extra == 'hybrid'
